das_ice/__init__.py
das_ice/io.py
das_ice/metadata.py
das_ice/mfp.py
das_ice/plot.py
das_ice/processes.py
das_ice/signal/filter.py
das_ice/signal/picker.py
das_ice-0.3.10.dist-info/METADATA
das_ice-0.3.10.dist-info/WHEEL
das_ice-0.3.10.dist-info/licenses/LICENSE
das_ice-0.3.10.dist-info/RECORD
