Metadata-Version: 2.4
Name: das-ice
Version: 0.3.10
Summary: Python librairy to process DAS data
License-File: LICENSE
Author: Thomas Chauve
Author-email: thomas.chauve@univ-grenoble-alpes.fr
Requires-Python: >=3.11,<4.0
Classifier: Programming Language :: Python :: 3
Classifier: Programming Language :: Python :: 3.11
Classifier: Programming Language :: Python :: 3.12
Classifier: Programming Language :: Python :: 3.13
Classifier: Programming Language :: Python :: 3.14
Provides-Extra: docs
Requires-Dist: Sphinx (>=7.4.0,<8.0.0) ; extra == "docs"
Requires-Dist: bokeh
Requires-Dist: dask
Requires-Dist: distributed
Requires-Dist: h5py
Requires-Dist: jax
Requires-Dist: jaxlib
Requires-Dist: jinja2
Requires-Dist: llvmlite
Requires-Dist: matplotlib
Requires-Dist: natsort
Requires-Dist: nbsphinx (>=0.9.3,<0.10.0) ; extra == "docs"
Requires-Dist: numba
Requires-Dist: pandoc (>=2.4,<3.0) ; extra == "docs"
Requires-Dist: pkginfo
Requires-Dist: platformdirs
Requires-Dist: plotly
Requires-Dist: python-docs-theme (>=2024.6,<2025.0) ; extra == "docs"
Requires-Dist: scipy
Requires-Dist: sphinx-rtd-theme (>=2.0.0,<3.0.0) ; extra == "docs"
Requires-Dist: torch
Requires-Dist: twine (>=5.1.1,<6.0.0) ; extra == "docs"
Requires-Dist: xarray
Requires-Dist: xdas
